Workbook
Name _MON_1232266605: APTITUDES!#REF!
Name _MON_1232266605: 'Intérêts et occupations'!#REF!
Name _MON_1232266605: PERSONNALITÉ!#REF!

Sheet Intérêts et activités
B1: Il faut considérer, lorsque vous remplissez le test, que vous avez les capacités, les connaissances et la formation nécessaires pour effectuer ces activités. Il ne faut pas tenir compte que de votre goût. Mettre un "1" sur la ligne vis-à-vis des activités que vous aimez ou que vous aimeriez pratiquer.
C2: 0 | D2: 1
A3: R(1/6) | B3: 0 : si l’activité vous déplaît ou vous laisse indifférent Sinon 1 | C3: 0/1
A4: 1. | B4: Planter, entretenir des arbres, des arbustes, des fleurs, cultiver le sol.
A5: 2. | B5: Effectuer des réparations électriques ou électroniques.
A6: 3. | B6: Faire de la couture.
A7: 4. | B7: Réparer des autos.
A8: 5. | B8: Fabriquer des objets avec du bois.
A9: 6. | B9: Conduire un camion ou un tracteur.
A10: 7. | B10: Faire des déménagements.
A11: 8. | B11: Entretenir ou réparer de la plomberie ou des systèmes de ventilation ou de chauffage.
A12: 9. | B12: Travailler avec des animaux.
A13: 10. | B13: Travailler à l’extérieur (travailler dans différentes conditions climatiques).
A14: 11. | B14: Travailler avec de la machinerie.
A15: 12. | B15: Préparer des repas, des banquets.
... A18: 15. | B18: Suivre un cours de dessin mécanique.
B19: Total des R : | C19: =SUM(C4:C18) -> 0
A21: I(2/6) | B21: 0 : si l’activité vous déplaît ou vous laisse indifférent Sinon 1 | C21: 0/1
A22: 1. | B22: Lire des revues scientifiques ou spécialisées.
A23: 2. | B23: Faire des expériences sur le comportement des animaux.
A24: 3. | B24: Effectuer des analyses en laboratoire.
A25: 4. | B25: Établir un diagnostic de maladie chez des patients.
A26: 5. | B26: Suivre des cours de sciences (chimie, biologie, physique).
A27: 6. | B27: Concevoir un barrage électrique, un pont, une autoroute, etc.
A28: 7. | B28: Faire des recherches scientifiques pour satisfaire ma curiosité.
A29: 8. | B29: Résoudre des problèmes mathématiques.
A30: 9. | B30: Concevoir un plan de reboisement.
A31: 10. | B31: Produire un rapport sur l’évolution économique d’une région.
A32: 11. | B32: Faire de la programmation informatique.
A33: 12. | B33: Planifier des soins ou des traitements à donner à des patients.
... A36: 15. | B36: Expérimenter de nouvelles cultures végétales.
B37: Total des I : | C37: =SUM(C22:C36) -> 0
A39: A (3/6) | B39: 0 : si l’activité vous déplaît ou vous laisse indifférent Sinon 1 | C39: 0/1
A40: 1. | B40: Écrire des romans, des articles de journaux.
A41: 2. | B41: Interpréter ou mettre en scène une pièce de théâtre.
A42: 3. | B42: Dessiner des meubles, des plans de maison, des décors, etc.
A43: 4. | B43: Créer des pièces d’artisanat.
A44: 5. | B44: Jouer dans un orchestre.
A45: 6. | B45: Créer une nouvelle coupe de cheveux ou un nouveau vêtement.
A46: 7. | B46: Faire de la photographie publicitaire ou artistique.
A47: 8. | B47: Apprendre des langues.
A48: 9. | B48: Imaginer une bande dessinée.
A49: 10. | B49: Concevoir et réaliser des arrangements de fleurs.
A50: 11. | B50: Peindre des tableaux pour une exposition.
A51: 12. | B51: Écrire des critiques de pièces de théâtre, de films, de livres, etc.
... A54: 15. | B54: Imaginer de nouvelles façons de faire les choses.
B55: Total des A : | C55: =SUM(C40:C54) -> 0
A57: S (4/6) | B57: 0 : si l’activité vous déplaît ou vous laisse indifférent Sinon 1 | C57: 0/1
A58: 1. | B58: Rencontrer des gens pour les aider à résoudre leurs problèmes personnels.
A59: 2. | B59: S’engager dans des organismes sociaux communautaires.
A60: 3. | B60: Travailler dans une garderie d’enfants.
A61: 4. | B61: Agir à titre d’hôte lors d’un congrès.
A62: 5. | B62: Tenir un kiosque d’information.
A63: 6. | B63: Offrir un service d’aide téléphonique (ex. : Au bout du fil).
A64: 7. | B64: Consulter des gens à propos de leurs besoins (sondage, enquête, etc.)
A65: 8. | B65: Échanger des idées avec d’autres personnes.
A66: 9. | B66: S’occuper de personnes handicapées physiques.
A67: 10. | B67: Animer un groupe.
A68: 11. | B68: Soigner un malade.
A69: 12. | B69: Aider les délinquants à se réhabiliter.
... A72: 15. | B72: Enseigner aux enfants, aux adolescents, aux adultes.
B73: Total des S : | C73: =SUM(C58:C72) -> 0
A75: E(5/6) | B75: 0 : si l’activité vous déplaît ou vous laisse indifférent Sinon 1 | C75: 0/1
A76: 1. | B76: Vendre un produit ou une idée.
A77: 2. | B77: Mettre sur pied son propre commerce.
A78: 3. | B78: Donner des conférences.
A79: 4. | B79: Acheter pour le compte d’un grand magasin.
A80: 5. | B80: Marchander.
A81: 6. | B81: Diriger du personnel.
A82: 7. | B82: Défendre une cause.
A83: 8. | B83: Faire de la sélection de candidats.
A84: 9. | B84: S’engager à fond dans des activités sociales au travail ou dans son quartier.
A85: 10. | B85: Diriger une entreprise financière.
A86: 11. | B86: Lancer un nouveau produit.
A87: 12. | B87: Fonder un club de consommateurs, une association de protection de l’environnement, une activité de récupération de papier.
... A90: 15. | B90: Lancer un concours de promotion, une campagne de publicité.
B91: Total des E : | C91: =SUM(C76:C90) -> 0
A93: C(6/6) | B93: 0 : si l’activité vous déplaît ou vous laisse indifférent Sinon 1 | C93: 0/1
A94: 1. | B94: Dactylographier ou réviser des lettres ou des rapports.
A95: 2. | B95: Effectuer des tâches clairement définies.
A96: 3. | B96: Faire fonctionner toutes sortes de machines de bureau.
A97: 4. | B97: Vérifier des rapports financiers.
A98: 5. | B98: Recevoir et faire des appels téléphoniques.
A99: 6. | B99: Classer des lettres, des rapports, des dossiers.
A100: 7. | B100: S’adonner à des activités régulières.
A101: 8. | B101: Faire des opérations de mathématiques pour préparer des rapports ou faire la tenue de livres.
A102: 9. | B102: Garder son espace de travail à l’ordre.
A103: 10. | B103: Manipuler un appareil de traitement de texte.
A104: 11. | B104: Maintenir un système de classement (archive, bibliothèque, bureau, etc.).
A105: 12. | B105: Faire un inventaire et passer des commandes.
... A108: 15. | B108: Établir des comptes rendus des dépenses.
B109: Total des C : | C109: =SUM(C94:C108) -> 0

Sheet Intérêts et occupations
B1: mettre un "1" sur les lignes situées vis-à-vis des professions qui vous conviendraient. Ne vous préoccupez pas de savoir si vous pouvez réussir dans tel métier ou dans telle profession ni de votre préparation actuelle. Ne songez ni au salaire ni à l’avancement. Bref, demandez-vous seulement si le travail en question est susceptible de vous plaire.
C2: 0 | D2: 1
A3: R(1/6) | B3: 1: métier peut me plaire Sinon 0 | C3: 0/1
A4: 1. | B4: Mécanicien d’auto
A5: 2. | B5: Éleveur de bétail
A6: 3. | B6: Technicien dentaire
A7: 4. | B7: Couturier en usine
A8: 5. | B8: Travailleur de la construction (menuiserie
A9: 6. | B9: Technicien en aménagement de la faune
A10: 7. | B10: Horloger
A11: 8. | B11: Technicien du meuble et du bois ouvré (ébéniste)
A12: 9. | B12: Plombier
A13: 10. | B13: Technicien en mécanique du bâtiment (spécialiste en réfrigération et climatisation)
A14: 11. | B14: Conducteur
A15: 12. | B15: Technicien en entretien d’aéronefs
... A18: 15. | B18: Cuisinier
B19: Total des R : | C19: =SUM(C4:C18) -> 0
A21: I(2/6) | B21: 1: métier peut me plaire Sinon 0 | C21: 0/1
A22: 1. | B22: Ingénieur en chimie, physique
A23: 2. | B23: Technicien en laboratoire médical
A24: 3. | B24: Chercheur scientifique
A25: 4. | B25: Technicien en radiologie (rayons X)
A26: 5. | B26: Biologiste
A27: 6. | B27: Technicien en informatique (programmeur)
A28: 7. | B28: Médecin vétérinaire
A29: 8. | B29: Technicien en transformation de produits forestiers (spécialiste dans la fabrication contreplaquée)
A30: 9. | B30: Météorologiste
A31: 10. | B31: Technicien en chimie analytique (analyse de nouveaux produits chimiques)
A32: 11. | B32: Astronome
A33: 12. | B33: Technicien en dessin de conception mécanique (dessin industriel)
... A36: 15. | B36: Botaniste
B37: Total des I : | C37: =SUM(C22:C36) -> 0
A39: A (3/6) | B39: 1: métier peut me plaire Sinon 0 | C39: 0/1
A40: 1. | B40: Musicien
A41: 2. | B41: Écrivain
A42: 3. | B42: Fleuriste
A43: 4. | B43: Journaliste
A44: 5. | B44: Décorateur d’intérieur
A45: 6. | B45: Compositeur (musique)
A46: 7. | B46: Mannequin
A47: 8. | B47: Photographe
A48: 9. | B48: Graphiste
A49: 10. | B49: Directeur de publicité
A50: 11. | B50: Architecte
A51: 12. | B51: Interprète
... A54: 15. | B54: Professeur de dessin
B55: Total des A : | C55: =SUM(C40:C54) -> 0
A57: S (4/6) | B57: 1: métier peut me plaire Sinon 0 | C57: 0/1
A58: 1. | B58: Infirmier auxiliaire
A59: 2. | B59: Agent à l’aide sociale
A60: 3. | B60: Travailleur social
A61: 4. | B61: Barman
A62: 5. | B62: Professeur à l’élémentaire
A63: 6. | B63: Technicien en loisirs
A64: 7. | B64: Technicien en garderie d’enfants
A65: 8. | B65: Orthopédagogue (correction des troubles de l’apprentissage)
A66: 9. | B66: Esthéticienne
A67: 10. | B67: Technicien policier
A68: 11. | B68: Médecin généraliste (de famille)
A69: 12. | B69: Directeur de personnel
... A72: 15. | B72: Technicien en réadaptation physique
B73: Total des S : | C73: =SUM(C58:C72) -> 0
A75: E(5/6) | B75: 1: métier peut me plaire Sinon 0 | C75: 0/1
A76: 1. | B76: Agent de publicité (marketing)
A77: 2. | B77: Avocat
A78: 3. | B78: Agent de bord
A79: 4. | B79: Commis-vendeur
A80: 5. | B80: Directeur d’une entreprise
A81: 6. | B81: Chef de rayons de supermarché
A82: 7. | B82: Politicien
A83: 8. | B83: Directeur des ventes
A84: 9. | B84: Vendeur d’assurances
A85: 10. | B85: Gérant d’hôtel
A86: 11. | B86: Technicien en tourisme
A87: 12. | B87: Propriétaire d’un commerce
... A90: 15. | B90: Agent de voyages
B91: Total des E : | C91: =SUM(C76:C90) -> 0
A93: C(6/6) | B93: 1: métier peut me plaire Sinon 0 | C93: 0/1
A94: 1. | B94: Commis-comptable
A95: 2. | B95: Technicien en finance (comptabilité)
A96: 3. | B96: Opérateur en informatique
A97: 4. | B97: Secrétaire de service juridique, médical
A98: 5. | B98: Archiviste médical
A99: 6. | B99: Commis aux renseignements
A100: 7. | B100: Bibliotechnicien
A101: 8. | B101: Expert en impôt
A102: 9. | B102: Caissier de banque
A103: 10. | B103: Réceptionniste
A104: 11. | B104: Commis au service de la paie
A105: 12. | B105: Gérant du service de crédit
... A108: 15. | B108: Technicien juridique (aux greffes)
B109: Total des C : | C109: =SUM(C94:C108) -> 0
A130: 1. | B130: Dactylographier ou réviser des lettres ou des rapports.
A131: 2. | B131: Effectuer des tâches clairement définies.
A132: 3. | B132: Faire fonctionner toutes sortes de machines de bureau.
A133: 4. | B133: Vérifier des rapports financiers.
A134: 5. | B134: Recevoir et faire des appels téléphoniques.
A135: 6. | B135: Classer des lettres, des rapports, des dossiers.
A136: 7. | B136: S’adonner à des activités régulières.
A137: 8. | B137: Faire des opérations de mathématiques pour préparer des rapports ou faire la tenue de livres.
...

Sheet APTITUDES
B1: Voici une liste d’aptitudes, d’habiletés, de talents qui sont en rapport avec des occupations. Évaluez-vous le plus objectivement possible, 1, 3, 5 le chiffre qui correspond au niveau d’aptitudes que vous pensez posséder. Ne vous sous-estimez pas et ne vous surestimez pas. Soyez honnête envers vous-même. Évaluez votre capacité réelle aujourd’hui.
C2: 1 | D2: 3 | E2: 5
A3: R(1/6) | B3: Faible (1) Moyen (3) Fort(5) | C3: 1 / 3 / 5 ?
A4: 1. | B4: Ma capacité à soulever des poids lourds est :
A5: 2. | B5: Ma capacité à utiliser des outils, des objets, des machines avec précision est :
A6: 3. | B6: Mon habileté à conduire de gros véhicules (camions) est :
A7: 4. | B7: Mon aptitude à lire des plans est :
A8: 5. | B8: Mon habileté dans les mouvements demandant à voir et à manipuler en même temps est :
A9: 6. | B9: La rapidité de mes réflexes est :
A10: 7. | B10: Mon habileté à faire des réparations est :
A11: 8. | B11: Ma capacité à m'occuper de l'élevage d'animaux est :
A12: 9. | B12: Ma capacité à installer et à manipuler divers outils, machines ou appareils est :
A13: 10. | B13: Ma capacité à comprendre le fonctionnement des éléments de base de tout ouvrage mécanique, électrique (moteurs, turbides, pompes) est :
B14: Total des R : | C14: =SUM(C4:C13) -> 0
A16: I(2/6) | B16: Faible (1) Moyen (3) Fort(5) | C16: 1 / 3 / 5 ?
A17: 1. | B17: Mes aptitudes en mathématiques sont :
A18: 2. | B18: Mes capacités en sciences (biologie, physique) sont :
A19: 3. | B19: Ma capacité à me concentrer sur une tâche abstraite est :
A20: 4. | B20: Ma capacité d'analyse est :
A21: 5. | B21: Ma capacité de synthèse (résumer) est :
A22: 6. | B22: Mon talent à rédiger clairement un texte est :
A23: 7. | B23: Ma capacité à comprendre des directives rapidement est :
A24: 8. | B24: Mon habileté à apprendre de nouveaux sujets avec facilité est :
A25: 9. | B25: Mon habileté à résoudre des problèmes abstraits est :
A26: 10. | B26: Mon habileté à faire des travaux de laboratoire est :
B27: Total des I : | C27: =SUM(C17:C26) -> 0
A29: A (3/6) | B29: Faible (1) Moyen (3) Fort(5) | C29: 1 / 3 / 5 ?
A30: 1. | B30: Ma capacité à me représenter la forme d'objets en deux ou trois dimensions est :
A31: 2. | B31: Ma facilité à apprendre des langues, y compris ma langue maternelle, est :
A32: 3. | B32: Mon aptitude en arts plastiques (dessin, peinture) est :
A33: 4. | B33: Mon aptitude dans les arts de la scène (théâtre) est :
A34: 5. | B34: Ma capacité d'inventer, de créer, de concevoir est :
A35: 6. | B35: Ma capacité à accepter la critique est :
A36: 7. | B36: Ma capacité à travailler par moi-même est :
A37: 8. | B37: Mon aptitude à exprimer concrètement mes idées créatrices de la façon dont je veux (dessin, arts) est :
A38: 9. | B38: Mon aptitude à tolérer l'insécurité (peur du lendemain) est :
A39: 10. | B39: Mon habileté à observer les légères différences de forme ou de teinte est :
B40: Total des A : | C40: =SUM(C30:C39) -> 0
A42: S (4/6) | B42: Faible (1) Moyen (3) Fort(5) | C42: 1 / 3 / 5 ?
A43: 1. | B43: Mon aptitude à travailler en équipe est :
A44: 2. | B44: Mon sens de l'organisation est :
A45: 3. | B45: Ma faculté de prévoir, de deviner (intuition) est :
A46: 4. | B46: Ma capacité d'animer un groupe est :
A47: 5. | B47: Ma capacité à maintenir des relations suivies avec les gens est :
A48: 6. | B48: Mon aptitude à être touché par les émotions des autres tout en demeurant objectif (empathie) est :
A49: 7. | B49: Ma capacité à réagir correctement devant les situations qui se présentent est :
A50: 8. | B50: Ma capacité à aider les autres, à les comprendre, à les écouter est :
A51: 9. | B51: Ma capacité à expliquer les choses clairement est :
A52: 10. | B52: Ma capacité à communiquer avec les autres est :
B53: Total des S : | C53: =SUM(C43:C52) -> 0
A55: E(5/6) | B55: Faible (1) Moyen (3) Fort(5) | C55: 1 / 3 / 5 ?
A56: 1. | B56: Ma facilité à m'exprimer en public est :
A57: 2. | B57: Mon talent pour vendre est :
A58: 3. | B58: Mon sens des affaires est :
A59: 4. | B59: Mon habileté à diriger, à mener les autres est :
A60: 5. | B60: Ma capacité à prendre une décision seule est :
A61: 6. | B61: Mon habileté à me faire valoir en société est :
A62: 7. | B62: Mon aptitude à défendre une cause est :
A63: 8. | B63: Ma capacité à être le premier à proposer ou à faire quelque choseest :
A64: 9. | B64: Mon talent pour persuader les gens est :
A65: 10. | B65: Ma capacité à demeurer enthousiaste et énergique en situation difficile est :
B66: Total des E : | C66: =SUM(C56:C65) -> 0
A68: C(6/6) | B68: Faible (1) Moyen (3) Fort(5) | C68: 1 / 3 / 5 ?
A69: 1. | B69: Ma capacité à me conformer aux règles établies est :
A70: 2. | B70: Mon aptitude à travailler avec précision est :
A71: 3. | B71: Ma capacité à disposer les choses selon leur rang est :
A72: 4. | B72: Mon aptitude en français est :
A73: 5. | B73: Mon aptitude à travailler avec les chiffres est :
A74: 6. | B74: Ma capacité à observer les détails est :
A75: 7. | B75: Ma capacité à m'adapter à un travail routinier est :
A76: 8. | B76: Ma capacité à tenir des dossiers et des registres à jour est :
A77: 9. | B77: Ma capacité à comprendre et à exécuter des instructions est :
A78: 10. | B78: Mon aptitude à comprendre les structures administratives est :
B79: Total des C : | C79: =SUM(C69:C78) -> 0

Sheet PERSONNALITÉ
B1: Voici une liste de traits de caractère, d’attitudes et de tendances personnelles. Mettre un "1" sur la ligne correspondant aux énoncés qui s’appliquent à vous, qui décrivent votre façon d’agir. Il est important de répondre le plus honnêtement possible.
C2: 0 | D2: 1
A3: R(1/6) | B3: s’applique à moi (1) sinon (0) | C3: 0 / 1 ?
A4: 1. | B4: Je suis conformiste, je me plie facilement aux règlements du milieu où je vis.
A5: 2. | B5: Généralement, j'évite de me faire remarquer.
A6: 3. | B6: J'aime les choses matérielles, concrètes.
A7: 4. | B7: Dans mon travail ou ailleurs, je me montre persistant.
A8: 5. | B8: Je démontre un esprit d'équipe pratique et je préfère agir plutôt que de bavarder.
A9: 6. | B9: Je suis d'un naturel réservé; pour savoir mon opinion, on doit me le demander.
A10: 7. | B10: Je suis porté à ménager et à prendre soin de mes biens.
A11: 8. | B11: Je suis stable dans mes opinions, ma façon de vivre, mes amitiés.
A12: 9. | B12: Je me présente toujours au naturel, tel que je suis.
A13: 10. | B13: Avec mon entourage, je suis franc et sincère.
B14: Total des R : | C14: =SUM(C2:C13) -> 0
A16: I(2/6) | B16: s’applique à moi (1) sinon (0) | C16: 0 / 1 ?
A17: 1. | B17: J'analyse les idées, les événements, ce qui se passe autour de moi.
A18: 2. | B18: J'ai l'esprit critique et n'accepte pas facilement n'importe quelle idée.
A19: 3. | B19: Je suis d'un naturel très curieux sur à peu près tout.
A20: 4. | B20: Je tiens à mon indépendance sur le plan des idées, du travail, etc.
A21: 5. | B21: Les gens me considèrent comme une personne intellectuelle plutôt qu'émotive.
A22: 6. | B22: J'ai l'esprit inventif : il m'arrive souvent de trouver une solution originale et efficace à un problème.
A23: 7. | B23: J'aime la précision dans tout ce que je fais.
A24: 8. | B24: Je demeure réservé dans l'expression de mes opinions, de mes sentiments et dans mes actes.
A25: 9. | B25: Avant toute décision, je réunis le maximum d'information possible.
A26: 10. | B26: Je préfère comprendre les choses à fond plutôt que d’agir sans réfléchir.
B27: Total des I : | C27: =SUM(C15:C26) -> 0
A29: A (3/6) | B29: s’applique à moi (1) sinon (0) | C29: 0 / 1 ?
A30: 1. | B30: Mes amis me considèrent compliqué.
A31: 2. | B31: Dans mes diverses activités, je manque souvent d'ordre.
A32: 3. | B32: Dans mes travaux, je fais preuve d'originalité, d'imagination et d'intuition.
A33: 4. | B33: Je suis d'un caractère impulsif.
A34: 5. | B34: Mes émotions sont généralement intenses.
A35: 6. | B35: Je suis porté à tout idéaliser et à chercher la perfection.
A36: 7. | B36: J'agis et je pense souvent de façon non conformiste, c'est-à-dire différemment des autres.
A37: 8. | B37: J'exprime mes sentiments par l'entremise de la musique, des beaux-arts, de la poésie, etc.
A38: 9. | B38: Les lendemains ne m'inquiètent pas : je vis au jour le jour.
A39: 10. | B39: J'ai besoin de beaucoup de liberté d'action dans tout ce que j'entreprends.
B40: Total des A : | C40: =SUM(C28:C39) -> 0
A42: S (4/6) | B42: s’applique à moi (1) sinon (0) | C42: 0 / 1 ?
A43: 1. | B43: Quand un problème se pose, je préfère le régler par la discussion et l'entente avec les gens qui m'entourent.
A44: 2. | B44: Je sais me montrer souple, conciliant.
A45: 3. | B45: Mes amis me considèrent comme bienveillant et compréhensif.
A46: 4. | B46: Généralement, les gens peuvent compter sur ma coopération.
A47: 5. | B47: Les gens me qualifient de sociable et de sympathique.
A48: 6. | B48: Je suis d'un naturel serviable.
A49: 7. | B49: J'accepte et j'assume des responsabilités.
A50: 8. | B50: On me considère généreux.
A51: 9. | B51: Dans la majorité des circonstances, je suis perspicace, clairvoyant.
A52: 10. | B52: Dans l'action comme dans la façon de m'exprimer, je montre de la délicatesse.
B53: Total des S : | C53: =SUM(C41:C52) -> 0
A55: E(5/6) | B55: s’applique à moi (1) sinon (0) | C55: 0 / 1 ?
A56: 1. | B56: L'ambition ne m'effraie pas.
A57: 2. | B57: Je suis un optimiste né.
A58: 3. | B58: Je suis sociable et populaire; je parle à tout le monde.
A59: 4. | B59: Je défends toujours mes opinions.
A60: 5. | B60: Il m'arrive souvent de me montrer autoritaire.
A61: 6. | B61: L'aventure m'attire beaucoup.
A62: 7. | B62: Généralement, je suis sûr de moi.
A63: 8. | B63: Mes impulsions me dictent souvent ma conduite.
A64: 9. | B64: J'aime être responsable d'activités.
A65: 10. | B65: Même dans des situations critiques ou tendues, je sais prendre l'initiative nécessaire.
B66: Total des E : | C66: =SUM(C54:C65) -> 0
A68: C(6/6) | B68: s’applique à moi (1) sinon (0) | C68: 0 / 1 ?
A69: 1. | B69: Je suis maître de moi, d'un calme exemplaire.
A70: 2. | B70: J'obéis facilement aux règlements et aux ordres.
A71: 3. | B71: Dans mes travaux, je suis persistant et consciencieux.
A72: 4. | B72: Je m'efforce de me montrer compétent dans ce qu'on exige de moi.
A73: 5. | B73: L'esprit concret et pratique me guide.
A74: 6. | B74: J'agis méthodiquement dans tout ce que je fais.
A75: 7. | B75: Je travaille avec beaucoup de soin.
A76: 8. | B76: Je suis timide et je préfère garder pour moi mes sentiments, mes émotions et mes idées.
A77: 9. | B77: J'aime recevoir des instructions bien claires qui me permettent de savoir exactement ce qu'on attend de moi.
A78: 10. | B78: Mon aptitude à comprendre les structures administratives est :
B79: Total des C : | C79: =SUM(C67:C78) -> 0

Sheet COMPILATION 
D1: Feuille de compilation du profil personnel
A3: Résultats | B3: R | C3: I | D3: A | E3: S | F3: E | G3: C
A4: Intérêts — activités | B4: ='Intérêts et activités'!C19 -> 0 | C4: ='Intérêts et activités'!C37 -> 0 | D4: ='Intérêts et activités'!C55 -> 0 | E4: ='Intérêts et activités'!C73 -> 0 | F4: ='Intérêts et activités'!C91 -> 0 | G4: ='Intérêts et activités'!C109 -> 0
A5: Intérêts — occupations | B5: ='Intérêts et occupations'!C19 -> 0 | C5: ='Intérêts et occupations'!C37 -> 0 | D5: ='Intérêts et occupations'!C55 -> 0 | E5: ='Intérêts et occupations'!C73 -> 0 | F5: ='Intérêts et occupations'!C91 -> 0 | G5: ='Intérêts et occupations'!C109 -> 0
A6: Aptitudes | B6: =APTITUDES!C14 -> 0 | C6: =APTITUDES!C27 -> 0 | D6: =APTITUDES!C40 -> 0 | E6: =APTITUDES!C53 -> 0 | F6: =APTITUDES!C66 -> 0 | G6: =APTITUDES!C79 -> 0
A7: Personnalité | B7: =PERSONNALITÉ!C14 -> 0 | C7: =PERSONNALITÉ!C27 -> 0 | D7: =PERSONNALITÉ!C40 -> 0 | E7: =PERSONNALITÉ!C53 -> 0 | F7: =PERSONNALITÉ!C66 -> 0 | G7: =PERSONNALITÉ!C79 -> 0
A8: Total | B8: =SUM(B4:B7) -> 0 | C8: =SUM(C4:C7) -> 0 | D8: =SUM(D4:D7) -> 0 | E8: =SUM(E4:E7) -> 0 | F8: =SUM(F4:F7) -> 0 | G8: =SUM(G4:G7) -> 0
D10: Les 3 totaux les plus élevés vous donnent votre code global
A12: RIASEC | B12: : | C12: =CHOOSE( MATCH(LARGE($B$8:$G$8,1),$B$8:$G$8,0), "R","I","A","S","E","C") -> R | D12: - | E12: =CHOOSE( MATCH(LARGE($B$8:$G$8,2),$B$8:$G$8,0), "R","I","A","S","E","C") -> R | F12: - | G12: =CHOOSE( MATCH(LARGE($B$8:$G$8,3),$B$8:$G$8,0), "R","I","A","S","E","C") -> R

Sheet RÉMY
A1: Rémy aime accomplir essentiellement des tâches manuelles et physiques. Il travaille davantage avec des objets (outils, machinerie, équipement, etc.). Il construit, répare ou manipule des objets. Il aime voir les résultats de son travail et poser des gestes concrets. Il a de bonnes habiletés manuelles et une bonne endurance physique.
A2: Prends connaissance des caractéristiques qui décrivent bien Rémy. Mettre un "1" sur vis-à-vis de celles qui te représentent.
A3: Qualités | B3: 0/1 | C3: Aptitudes | D3: 0/1 | E3: Valeurs | F3: 0/1 | G3: Champs d'intérêt | H3: 0/1 | I3: Métiers qui intéressent Rémy | J3: 0/1
A4: Énergique | C4: Dextérité manuelle | E4: Le plaisir | G4: Manipulation de machines | I4: Mécanicien
A5: Aventureux | C5: Sens de la mécanique | E5: L'action | G5: Travail avec des objets | I5: Charpentier-menuisier
A6: Patient | C6: Bonne perception spatiale | E6: Prendre des risques | G6: Utilisation d'outils | I6: Aide-fleuriste
A7: Actif | C7: Coordination visuomotrice | E7: La compétition | G7: Mécanique et électronique | I7: Ébéniste
A8: Courageux | C8: Manipulation d'outils | E8: La bonne forme physique | G8: Travail concret | I8: Chef de train
A9: Débrouillard | C9: Sens de la finition et de la minutie | E9: Le sport | G9: Dessin technique | I9: Technicienne d'entretien d'aéronefs
A10: Inventif | C10: Souci du détail et de la précision | G10: Travail extérieur et plein air | I10: Technologue en architecture
A11: Fiable | C11: Bonne forme physique | G11: Résoudre des problèmes menant à des résultats observables | I11: Commis à l'expédition de marchandises
A12: Direct | C12: Travail en équipe | G12: Construction | I12: Élagueur
A13: Total | B13: =SUM(B4:B12) -> 0 | C13: Total | D13: =SUM(D4:D12) -> 0 | E13: Total | F13: =SUM(F4:F12) -> 0 | G13: Total | H13: =SUM(H4:H12) -> 0 | I13: Total | J13: =SUM(J4:J12) -> 0
A14: Est-ce que mon profil personnel ressemble à celui de Rémy Oui ou Non (O/N)

Sheet ISAAC
A1: Isaac exécute essentiellement des tâches d’investigation. Il analyse et comprend des phénomènes, résout des problèmes, utilise ses connaissances, etc. Il se caractérise par son esprit scientifique. Il préfère les activités concernant l’observation, l’étude méthodique et rigoureuse des phénomènes physiques ou biologiques afin de les comprendre. Son ingéniosité et sa créativité le servent dans sa résolution de problèmes abstraits. Il s’intéresse à la science, la santé, les mathématiques et la recherche.
A2: Prends connaissance des caractéristiques qui décrivent bien Isaac. Mettre un "1" sur vis-à-vis de celles qui te représentent.
A3: Qualités | B3: 0/1 | C3: Aptitudes | D3: 0/1 | E3: Valeurs | F3: 0/1 | G3: Champs d'intérêt | H3: 0/1 | I3: Métiers qui intéressent Isaac | J3: 0/1
A4: Curieux | C4: Compréhension intellectuelle | E4: Le savoir | G4: Activités intellectuelles | I4: Biologiste
A5: Réfléchi | C5: Sens de l'observation | E5: Les connaissances générales | G5: Études | I5: Programmeur
A6: Logique | C6: Résolution de problèmes | E6: La scolarisation | G6: Expériences scientifiques | I6: Technicien en laboratoire de chimie
A7: Intellectuel | C7: Capacité d'analyse et de synthèse | E7: La rigueur | G7: Inventions et découvertes | I7: Technicien en électronique industriel
A8: Méthodique | C8: Capacité en communication | E8: Les défis intellectuels | G8: Haute technologie | I8: Technicien en génie aérospatial
A9: Autonome | C9: Capacité à identifier des problèmes | E9: La science | G9: Comprendre les choses | I9: Ingénieur mécanique
A10: Esprit critique | C10: Rigueur intellectuelle | G10: Aime s'interroger | I10: Inhalothérapeute
A11: Rigoureux | C11: Gestion de projet | G11: Chimie, physique, biologie, mathématique | I11: Pilote d'avion
A12: Appliqué | C12: Capacité à s'interroger | G12: Émettre des hypothèses | I12: Optométriste
A13: Total | B13: =SUM(B4:B12) -> 0 | C13: Total | D13: =SUM(D4:D12) -> 0 | E13: Total | F13: =SUM(F4:F12) -> 0 | G13: Total | H13: =SUM(H4:H12) -> 0 | I13: Total | J13: =SUM(J4:J12) -> 0
A14: Est-ce que mon profil personnel ressemble à celui de Isaac Oui ou Non (O/N)

Sheet ALAIN
A1: Alain effectue essentiellement des tâches de création. Il crée des œuvres (dessin, graphique, texte, musique, danse, etc.), les embellit et les interprète. Il aime travailler dans des milieux qui lui permettent avant tout d’exprimer ses idées, ses sentiments et sa créativité. Il s’intéresse à la musique, au théâtre, à l’écriture ou à la conception d’objet d’art. Rêveur imaginatif, émotif, idéaliste, un peu bohème, il recherche le changement, l’aventure et la nouveauté.
A2: Prends connaissance des caractéristiques qui décrivent bien Alain Mettre un "1" sur vis-à-vis de celles qui te représentent.
A3: Qualités | B3: 0/1 | C3: Aptitudes | D3: 0/1 | E3: Valeurs | F3: 0/1 | G3: Champs d'intérêt | H3: 0/1 | I3: Métiers qui intéressent Alain | J3: 0/1
A4: Original | C4: Sens esthétique | E4: L'art | G4: Littérature et langues | I4: Acteur
A5: Sensible | C5: Originalité dans les idées | E5: La liberté | G5: Musique | I5: Animateur 2D-3D
A6: Expressif | C6: Sensibilité personnelle | E6: La créativité | G6: Beaux-arts | I6: Architecte
A7: Indépendant | C7: Imagination et fabrication d'images | E7: La culture | G7: Publicité | I7: Caméraman
A8: Intuitif | C8: Talent pour la création | E8: Le changement | G8: Spectacle | I8: Concepteur de décor
A9: Créatif | C9: Facilité dans les arts plastiques | E9: L'ouverture d'esprit | G9: Photographie | I9: Designer de mode
A10: Innovateur | C10: Écriture créative | G10: Architecture | I10: Technicien du son
A11: Rêveur | C11: Capacité à analyser et à évaluer (œuvre d'art) | G11: Design | I11: Graphiste
A12: Curieux | C12: Talent en improvisation | G12: Arts numériques | I12: Photographe
A13: Total | B13: =SUM(B4:B12) -> 0 | C13: Total | D13: =SUM(D4:D12) -> 0 | E13: Total | F13: =SUM(F4:F12) -> 0 | G13: Total | H13: =SUM(H4:H12) -> 0 | I13: Total | J13: =SUM(J4:J12) -> 0
A14: Est-ce que mon profil personnel ressemble à celui de Alain Oui ou Non (O/N)

Sheet SIMON
A1: Simon aime accomplir essentiellement des tâches où il peut aider les gens et établir des liens de confiance avec eux. Il les écoute, les conseille, leur enseigne, les soigne, etc. Il est sensible aux problèmes de ses semblables et recherche les activités qui exigent des relations soutenues avec les gens. Il s’intéresse aux problèmes sociaux, psychologiques et moraux. Il aime le travail d’équipe, s'instruire, écouter ou soigner les autres. Il a de bonnes habiletés à comprendre et écouter les autres et à s’exprimer verbalement. Il possède un sens profond du respect d’autrui et du dévouement
A2: Prends connaissance des caractéristiques qui décrivent bien Simon Mettre un "1" sur vis-à-vis de celles qui te représentent.
A3: Qualités | B3: 0/1 | C3: Aptitudes | D3: 0/1 | E3: Valeurs | F3: 0/1 | G3: Champs d'intérêt | H3: 0/1 | I3: Métiers qui intéressent Simon | J3: 0/1
A4: Sociable | C4: Facilité à s'exprimer | E4: Le respect | G4: Sciences humaines (enseignement, politique) | I4: Agent de probation
A5: Dévoué | C5: Facilité à entretenir des relations | E5: L'authenticité | G5: Éducation et rééducation | I5: Enseignant
A6: Empathique | C6: Capacité à aider les autres | E6: L'écoute des autres | G6: Engagement social | I6: Expert en sinistre
A7: Communicatif | C7: Capacité d'écoute active | E7: La communication | G7: Animation et information | I7: Infirmier
A8: Compréhensif | C8: Facilité à comprendre les autres | E8: La compassion | G8: Restauration, hôtellerie, touriste | I8: Thérapeute en réadaptation physique
A9: Chaleureux | C9: Sens de la collaboration | E9: L'entraide | G9: Habiletés relationnelles | I9: Entraineur d'athlètes
A10: Serviable | C10: Facilité dans la résolution de conflits | G10: S'intéresse aux comportements humains | I10: Coiffeur
A11: Bienveillant | C11: Facilité à transmettre des connaissances | G11: Répondre aux besoins d'aide physique et psychologique | I11: Technicien en éducation spécialisée
A12: Coopératif | C12: Facilité dans la coordination d'activités | G12: Soins de santé | I12: Aide-éducatrice
A13: Total | B13: =SUM(B4:B12) -> 0 | C13: Total | D13: =SUM(D4:D12) -> 0 | E13: Total | F13: =SUM(F4:F12) -> 0 | G13: Total | H13: =SUM(H4:H12) -> 0 | I13: Total | J13: =SUM(J4:J12) -> 0
A14: Est-ce que mon profil personnel ressemble à celui de Simon Oui ou Non (O/N)

Sheet ÉMILIE
A1: Émile exécute essentiellement des tâches où elle peut influencer, mobiliser et diriger les gens. Elle recherche les contacts avec les autres pour les diriger,les influencer ou les persuader. Elle préfère les activités où elle peut exercer son leadership. Elle s’intéresse au monde des affaires, à la vente et à la politique. Elle a de bonnes habiletés verbales pour motiver et diriger les autres. Elle voit grand et elle sait s’imposer. Son esprit mathématique et son flair lui servent à évaluer les bonnes idées
A2: Prends connaissance des caractéristiques qui décrivent bien Émile Mettre un "1" sur vis-à-vis de celles qui te représentent.
A3: Qualités | B3: 0/1 | C3: Aptitudes | D3: 0/1 | E3: Valeurs | F3: 0/1 | G3: Champs d'intérêt | H3: 0/1 | I3: Métiers qui intéressent Émile | J3: 0/1
A4: Convaincant | C4: Facilité à diriger | E4: La réussite financière | G4: Économie, droit, politique | I4: Avocat
A5: Ambitieux | C5: Capacité à prendre des décisions | E5: Le statut social | G5: Affaires, commerce, finances | I5: Courtier immobilier
A6: Meneur | C6: Facilité à déterminer des objectifs | E6: Le prestige | G6: Mise en place de projets | I6: Directeur des ventes
A7: Déterminé | C7: Facilité à trouver des stratégies | E7: Le pouvoir | G7: Tâches de gestion | I7: Planificateur financier
A8: Compétitif | C8: Sens de la planification | E8: L'ambition | G8: Tâches administratives | I8: Vendeur
A9: Exigeant | C9: Talent de persuasion | E9: L'influence | G9: Aime planifier et diriger | I9: Concepteur de jeux vidéo
A10: Responsable | C10: Leadership | G10: Entrepreneuriat | I10: Conseiller en loisirs
A11: Confiant | C11: Sens de l'initiative et de l'organisation | G11: Vente, marketing, relations publiques | I11: Technicien en logistique du transport
A12: Énergique | C12: Esprit d'action, entrepreneuriat | G12: Aime influencer les autres | I12: Agent de bord
A13: Total | B13: =SUM(B4:B12) -> 0 | C13: Total | D13: =SUM(D4:D12) -> 0 | E13: Total | F13: =SUM(F4:F12) -> 0 | G13: Total | H13: =SUM(H4:H12) -> 0 | I13: Total | J13: =SUM(J4:J12) -> 0
A14: Est-ce que mon profil personnel ressemble à celui de Émile Oui ou Non (O/N)

Sheet CHRISTOPHE
A1: Christophe accomplit essentiellement des tâches où il peut travailler avec des données, de façon organisée et méthodique. Il classe des choses, traite des données, fait des suivis, réalise des tâches administratives, etc. Il aime faire un travail qui exige de se conformer à des règles précises où l’exactitude et la rapidité d’exécution sont importantes. Il ne laisse rien au hasard et exige des directives claires. Il s’intéresse à l’organisation, la gestion des données, la comptabilité et la finance. Il préfère le travail concret et répétitif. Il a de bonnes habiletés pour travailler avec des chiffres, pour l’analyse des données et pour la précision.
A2: Prends connaissance des caractéristiques qui décrivent bien Christophe Mettre un "1" sur vis-à-vis de celles qui te représentent.
A3: Qualités | B3: 0/1 | C3: Aptitudes | D3: 0/1 | E3: Valeurs | F3: 0/1 | G3: Champs d'intérêt | H3: 0/1 | I3: Métiers qui intéressent Christophe | J3: 0/1
A4: Raisonnable | C4: Rapidité d'exécution | E4: La sécurité d'emploi | G4: Classement et ordre | I4: Agent des services frontaliers
A5: Discret | C5: Sens de la précision | E5: L'honnêteté | G5: Tâches précises | I5: Arpenteur
A6: Pratique | C6: Sens de la méthode | E6: La famille | G6: Directives claires | I6: Caissier
A7: Ordonné | C7: Exactitude | E7: Le respect | G7: Travail méthodique | I7: Commis aux achats
A8: Fiable | C8: Mémoire du détail | E8: Le devoir | G8: Travail répétitif | I8: Comptable
A9: Minutieux | C9: Sens du classement de données | E9: Le souci de la précision | G9: Bureautique et informatique | I9: Technicien en documentation
A10: Consciencieux | C10: Souci de la présentation | G10: Gestion de données | I10: Agent de centre d'appel
A11: Conformiste | C11: Facilité à gérer son temps | G11: Assurance | I11: Conseiller technique (automobile)
A12: Efficace | C12: Facilité à rédiger des documents | G12: Aime les résultats prévisibles | I12: Préposé à la réception
A13: Total | B13: =SUM(B4:B12) -> 0 | C13: Total | D13: =SUM(D4:D12) -> 0 | E13: Total | F13: =SUM(F4:F12) -> 0 | G13: Total | H13: =SUM(H4:H12) -> 0 | I13: Total | J13: =SUM(J4:J12) -> 0
A14: Est-ce que mon profil personnel ressemble à celui de Christophe Oui/Non (O/N)

Sheet RÉFLEXION
B1: Qualités | C1: Aptitudes | D1: Valeurs | E1: Intérêt | F1: Métiers | G1: TOTAL
A2: REMY | B2: =RÉMY!B13 -> 0 | C2: =RÉMY!D$13 -> 0 | D2: =RÉMY!F$13 -> 0 | E2: =RÉMY!H$13 -> 0 | F2: =RÉMY!J$13 -> 0 | G2: =SUM(B2:F2) -> 0
A3: ISAAC | B3: =ISAAC!B13 -> 0 | C3: =ISAAC!D13 -> 0 | D3: =ISAAC!F13 -> 0 | E3: =ISAAC!H$13 -> 0 | F3: =ISAAC!J$13 -> 0 | G3: =SUM(B3:F3) -> 0
A4: ALAIN | B4: =ALAIN!B$13 -> 0 | C4: =ALAIN!D$13 -> 0 | D4: =ALAIN!F$13 -> 0 | E4: =ALAIN!H$13 -> 0 | F4: =ALAIN!J$13 -> 0 | G4: =SUM(B4:F4) -> 0
A5: SIMON | B5: =SIMON!B$13 -> 0 | C5: =SIMON!D$13 -> 0 | D5: =SIMON!F$13 -> 0 | E5: =SIMON!H$13 -> 0 | F5: =SIMON!J$13 -> 0 | G5: =SUM(B5:F5) -> 0
A6: EMILIE | B6: =ÉMILIE!B$13 -> 0 | C6: =ÉMILIE!D$13 -> 0 | D6: =ÉMILIE!F$13 -> 0 | E6: =ÉMILIE!H$13 -> 0 | F6: =ÉMILIE!J$13 -> 0 | G6: =SUM(B6:F6) -> 0
A7: CHRISTOPHE | B7: =CHRISTOPHE!B$13 -> 0 | C7: =CHRISTOPHE!D$13 -> 0 | D7: =CHRISTOPHE!F$13 -> 0 | E7: =CHRISTOPHE!H$13 -> 0 | F7: =CHRISTOPHE!J$13 -> 0 | G7: =SUM(B7:F7) -> 0
A9: Le personnage qui a le plus haut pointage : | D9: =INDEX($A$2:$A$7,MATCH(MAX($G$2:$G$7),$G$2:$G$7,0)) -> REMY
A10: Mon code RIASEC : | D10: ='COMPILATION '!C12 -> R | E10: ='COMPILATION '!E12 -> R | F10: ='COMPILATION '!G12 -> R
A12: La première lettre de mon RIASEC correspond au personnage qui avait le plus haut pointage : | G12: =IF(LEFT(D9,1)=LEFT(UPPER(D10),1),"OUI","NON") -> OUI
D13: =IF(G12="NON","La réponse est non. Explique pourquoi : ","")
